Abobabus.py
abobabus-0.0.2.dist-info/LICENSE.txt
abobabus-0.0.2.dist-info/METADATA
abobabus-0.0.2.dist-info/WHEEL
abobabus-0.0.2.dist-info/top_level.txt
abobabus-0.0.2.dist-info/RECORD
