Metadata-Version: 2.2
Name: Abobabus
Version: 0.0.2
Summary: Package to scrape Minecraft recipe to pandas dataframe
Author-email: Yaroslav Panov <pelmeshkasalo@gmail.com>
License: Copyright (c) 2025 Aboba
Classifier: Programming Language :: Python :: 3
Classifier: Operating System :: OS Independent
Requires-Python: >=3.10
License-File: LICENSE.txt
Requires-Dist: requests>=2.32.3
Requires-Dist: beautifulsoup4>=4.13.3
Requires-Dist: pandas>=2.2.3
